{
  "schemaVersion": "1.0.0",
  "id": "chapter-213",
  "number": "213",
  "name": "Unincorporated Business Tax",
  "title": {
    "id": "title-12",
    "number": "12",
    "name": "Taxation"
  },
  "sourceUrl": "https://www.cga.ct.gov/current/pub/chap_213.htm",
  "sections": [
    {
      "id": "group-12-269-to-12-284a",
      "kind": "group",
      "citation": null,
      "citations": [
        "12-269",
        "12-284a"
      ],
      "heading": "Secs. 12-269 to 12-284a. Unincorporated business tax.",
      "sourceUrl": "https://www.cga.ct.gov/current/pub/chap_213.htm#secs_12-269_to_12-284a",
      "status": "repealed",
      "content": {
        "body": [
          "Sections 12-269 to 12-284a , inclusive, are repealed."
        ],
        "sourceNotes": [
          "(1949 Rev., S. 1955–1965, 1968, 1969, 1971; 1953, S. 1113d, 1121d; June 1955, S. 1113d–1115d; 1957, P.A. 512, S. 1; 515, S. 5–7; 1959, P.A. 141, S. 1; 152, S. 99; 1961, P.A. 604, S. 5; February, 1965, P.A. 10; 314; 1967, P.A. 57, S. 30; 754, S. 21; 1969, P.A. 291, S. 1, 2; 388, S. 8; 758, S. 20; June, 1969, P.A. 1, S. 47; 1971, P.A. 872, S. 37, 149; P.A. 76-436, S. 314, 681; P.A. 77-614, S. 139, 610; P.A. 78-280, S. 2, 5, 127; P.A. 81-255, S. 36, 37.)"
        ],
        "history": [],
        "annotations": [],
        "plainText": "Sections 12-269 to 12-284a , inclusive, are repealed."
      }
    },
    {
      "id": "section-12-269",
      "kind": "section",
      "citation": "12-269",
      "citations": [
        "12-269"
      ],
      "heading": "12-269",
      "sourceUrl": "https://www.cga.ct.gov/current/pub/chap_213.htm#sec_12-269",
      "status": "repealed",
      "content": {
        "body": [
          "Secs. 12-269 to 12-284a. Unincorporated business tax. Sections 12-269 to 12-284a , inclusive, are repealed."
        ],
        "sourceNotes": [],
        "history": [],
        "annotations": [],
        "plainText": "Secs. 12-269 to 12-284a. Unincorporated business tax. Sections 12-269 to 12-284a , inclusive, are repealed."
      }
    },
    {
      "id": "section-12-284a",
      "kind": "section",
      "citation": "12-284a",
      "citations": [
        "12-284a"
      ],
      "heading": "12-284a",
      "sourceUrl": "https://www.cga.ct.gov/current/pub/chap_213.htm#sec_12-284a",
      "status": "repealed",
      "content": {
        "body": [
          "Secs. 12-269 to 12-284a. Unincorporated business tax. Sections 12-269 to 12-284a , inclusive, are repealed."
        ],
        "sourceNotes": [],
        "history": [],
        "annotations": [],
        "plainText": "Secs. 12-269 to 12-284a. Unincorporated business tax. Sections 12-269 to 12-284a , inclusive, are repealed."
      }
    }
  ]
}
